folder_classifier/__init__.py
folder_classifier/app.py
folder_classifier/classifier.py
folder_classifier/deploy.py
folder_classifier/dto.py
folder_classifier/util.py
folder_classifier-0.4.6.dist-info/METADATA
folder_classifier-0.4.6.dist-info/WHEEL
folder_classifier-0.4.6.dist-info/top_level.txt
folder_classifier-0.4.6.dist-info/RECORD
