Metadata-Version: 2.4
Name: folder-classifier
Version: 0.4.6
Summary: Deploy folder classifier API to a Ray cluster
Author: Crispin Almodovar
Author-email: 
Classifier: Programming Language :: Python :: 3
Classifier: License :: OSI Approved :: MIT License
Classifier: Operating System :: OS Independent
Requires-Python: >=3.12
